[
  {
    "id": 141665,
    "method": "delete",
    "comment": "hi4"
  },
  {
    "id": "7",
    "method": "delete",
    "comment": "f"
  },
  {
    "id": "74",
    "method": "delete",
    "comment": "sdf"
  },
  {
    "id": "76",
    "method": "delete",
    "comment": "mmn"
  },
  {
    "id": 14454,
    "method": "delete",
    "comment": "hi4"
  },
  {
    "id": 14555454,
    "method": "delete",
    "comment": "hi4"
  },
  {
    "id": 155454,
    "method": "delete",
    "comment": "hi4"
  },
  {
    "id": 154,
    "method": "delete",
    "comment": "hi4"
  },
  {
    "id": 158787874,
    "method": "delete",
    "comment": "hi4"
  },
  {
    "id": 1874444,
    "method": "delete",
    "comment": "hi4"
  },
  {
    "id": "34545",
    "method": "delete",
    "comment": "xdf"
  }
]